pythontohtml/__about__.py
pythontohtml/__init__.py
pythontohtml/_helpers.py
pythontohtml/htmlTags.py
pythontohtml-1.0.0.dist-info/METADATA
pythontohtml-1.0.0.dist-info/WHEEL
pythontohtml-1.0.0.dist-info/top_level.txt
pythontohtml-1.0.0.dist-info/RECORD
