Metadata-Version: 2.1
Name: pythontohtml
Version: 1.0.0
Summary: python functions to HTML
Home-page: https://github.com/hakiKhuva/pythontohtml
Author: Harkishan Khuva
Author-email: harkishankhuva02@gmail.com
License: MIT
Platform: UNKNOWN
Classifier: Programming Language :: Python :: 3
Requires-Python: >=3.6
